Metadata-Version: 2.1
Name: git-rebase-chain
Version: 0.1.1
Summary: UNKNOWN
Home-page: UNKNOWN
License: UNKNOWN
Platform: UNKNOWN
